windowsservice/__about__.py
windowsservice/__init__.py
windowsservice/service.py
windowsservice/utils.py
windowsservice-3.0.0.dist-info/METADATA
windowsservice-3.0.0.dist-info/WHEEL
windowsservice-3.0.0.dist-info/licenses/LICENSE.txt
windowsservice-3.0.0.dist-info/RECORD
