Metadata-Version: 2.4
Name: windowsservice
Version: 3.0.0
Summary: A Python package for building Windows services.
Project-URL: Homepage, https://github.com/hylkepostma/windowsservice
Project-URL: Documentation, https://github.com/hylkepostma/windowsservice#windowsservice
Author-email: Hylke Postma <info@hylkepostma.nl>
License-Expression: MIT
License-File: LICENSE.txt
Keywords: multiprocessing,pyinstaller,python,pywin32,service,windows,windowsservice
Classifier: Development Status :: 5 - Production/Stable
Classifier: Intended Audience :: Developers
Classifier: License :: OSI Approved :: MIT License
Classifier: Operating System :: Microsoft :: Windows
Classifier: Programming Language :: Python :: 3.13
Classifier: Programming Language :: Python :: 3.14
Classifier: Topic :: Software Development :: Build Tools
Requires-Python: >=3.13
Requires-Dist: pywin32==311
Provides-Extra: all
Requires-Dist: black; extra == 'all'
Requires-Dist: pyinstaller<7,>=6.5.0; extra == 'all'
Requires-Dist: pytest<10.0.0,>=7.2.0; extra == 'all'
Requires-Dist: ruff; extra == 'all'
Provides-Extra: dev
Requires-Dist: black; extra == 'dev'
Requires-Dist: ruff; extra == 'dev'
Provides-Extra: test
Requires-Dist: pyinstaller<7,>=6.5.0; extra == 'test'
Requires-Dist: pytest<10.0.0,>=7.2.0; extra == 'test'
